MANIFEST.in
README.md
RELEASE-VERSION
setup.py
version.py
kvlayer_mysql/__init__.py
kvlayer_mysql/_test_config.py
kvlayer_mysql.egg-info/PKG-INFO
kvlayer_mysql.egg-info/SOURCES.txt
kvlayer_mysql.egg-info/dependency_links.txt
kvlayer_mysql.egg-info/entry_points.txt
kvlayer_mysql.egg-info/requires.txt
kvlayer_mysql.egg-info/top_level.txt