Metadata-Version: 1.1
Name: kvlayer-mysql
Version: 0.1.1
Summary: table-oriented abstraction layer over key-value stores
Home-page: http://diffeo.com
Author: Diffeo, Inc.
Author-email: support@diffeo.com
License: MIT/X11 license http://opensource.org/licenses/MIT
Platform: UNKNOWN
Classifier: Development Status :: 3 - Alpha
Classifier: Topic :: Utilities
Classifier: License :: OSI Approved :: MIT License
